zensols/cnndmdb/__init__.py
zensols/cnndmdb/app.py
zensols/cnndmdb/cli.py
zensols/cnndmdb/corpus.py
zensols/cnndmdb/load.py
zensols/cnndmdb/resources/app.conf
zensols/cnndmdb/resources/cnndm.sql
zensols/cnndmdb/resources/default.conf
zensols/cnndmdb/resources/obj.yml
zensols.cnndmdb-0.0.1.dist-info/METADATA
zensols.cnndmdb-0.0.1.dist-info/WHEEL
zensols.cnndmdb-0.0.1.dist-info/entry_points.txt
zensols.cnndmdb-0.0.1.dist-info/top_level.txt
zensols.cnndmdb-0.0.1.dist-info/RECORD
