Metadata-Version: 2.1
Name: zensols.cnndmdb
Version: 0.0.1
Summary: Creates a SQLite database if the CNN and DailyMail summarization dataset.
Home-page: https://github.com/plandes/cnndmdb
Download-URL: https://github.com/plandes/cnndmdb/releases/download/v0.0.1/zensols.cnndmdb-0.0.1-py3-none-any.whl
Author: Paul Landes
Author-email: landes@mailc.net
Keywords: tooling
Requires-Dist: tensorflow
Requires-Dist: tensorflow-datasets
Requires-Dist: zensols.dbpg (~=1.1.0)
Requires-Dist: zensols.util (~=1.13.0)
